vistrans/__init__.py
vistrans/version.py
vistrans/models/__init__.py
vistrans/models/botnet.py
vistrans/models/vit.py
vistrans/util/__init__.py
vistrans/util/utils.py
vistrans-0.0.3.dist-info/LICENSE
vistrans-0.0.3.dist-info/METADATA
vistrans-0.0.3.dist-info/WHEEL
vistrans-0.0.3.dist-info/top_level.txt
vistrans-0.0.3.dist-info/RECORD
