Metadata-Version: 2.1
Name: vistrans
Version: 0.0.3
Summary: Unofficial implementations of transfomers models for vision.
Home-page: https://github.com/nachiket273/VisTrans
Author: Nachiket Tanksale
Author-email: nachiket.tanksale@gmail.com
License: UNKNOWN
Keywords: pytorch transformer vision python deep-learning
Platform: UNKNOWN
Classifier: Development Status :: 3 - Alpha
Classifier: Intended Audience :: Developers
Classifier: Intended Audience :: Education
Classifier: License :: OSI Approved :: MIT License
Classifier: Programming Language :: Python :: 3.6
Classifier: Programming Language :: Python :: 3.7
Classifier: Programming Language :: Python :: 3.8
Classifier: Topic :: Scientific/Engineering
Classifier: Topic :: Scientific/Engineering :: Artificial Intelligence
Classifier: Topic :: Software Development
Classifier: Topic :: Software Development :: Libraries
Classifier: Topic :: Software Development :: Libraries :: Python Modules
Requires-Python: >=3.6
Requires-Dist: torch (>=1.4)
Requires-Dist: torchvision
